gitlab_mcp/__init__.py
gitlab_mcp/connector.py
gitlab_mcp/count_projects.py
gitlab_mcp/project_stats.py
gitlab_mcp/server.py
gitlab_mcp-0.1.7.dist-info/METADATA
gitlab_mcp-0.1.7.dist-info/WHEEL
gitlab_mcp-0.1.7.dist-info/top_level.txt
gitlab_mcp-0.1.7.dist-info/RECORD
