Metadata-Version: 2.1
Name: gitlab-mcp
Version: 0.1.7
Summary: 一个用于Cursor IDE的GitLab操作服务
Home-page: https://github.com/yourusername/gitlab-mcp
Author: ansonglin
Author-email: songlin.an@dmall.com
Classifier: Programming Language :: Python :: 3
Classifier: License :: OSI Approved :: MIT License
Classifier: Operating System :: OS Independent
Requires-Python: >=3.6
Requires-Dist: requests>=2.25.1
Requires-Dist: python-gitlab>=3.0.0
Requires-Dist: typer>=0.9.0
Requires-Dist: urllib3>=2.0.0
Requires-Dist: mcp>=0.1.0
